bbwebservice/__init__.py
bbwebservice/app_utils.py
bbwebservice/callable_blueprint.py
bbwebservice/config_loader.py
bbwebservice/core.py
bbwebservice/global_state.py
bbwebservice/http_parser.py
bbwebservice/metrics.py
bbwebservice/special_media_type.py
bbwebservice/type_validation.py
bbwebservice/url_utils.py
bbwebservice/webserver.py
bbwebservice/worker_pool.py
bbwebservice-3.2.0.dist-info/METADATA
bbwebservice-3.2.0.dist-info/WHEEL
bbwebservice-3.2.0.dist-info/top_level.txt
bbwebservice-3.2.0.dist-info/RECORD
