Metadata-Version: 2.4
Name: bbwebservice
Version: 3.2.0
Summary: A bare bone webserver
Author: Lukas
Author-email: lukasogwalker@gmail.com
License: MIT
Classifier: Programming Language :: Python :: 3
Classifier: License :: OSI Approved :: MIT License
Classifier: Operating System :: OS Independent
Requires-Python: >=3.10
